update_notes_extractor/__init__.py
update_notes_extractor/main.py
update_notes_extractor/prompts.py
update_notes_extractor-2025.12.21225744.dist-info/METADATA
update_notes_extractor-2025.12.21225744.dist-info/WHEEL
update_notes_extractor-2025.12.21225744.dist-info/top_level.txt
update_notes_extractor-2025.12.21225744.dist-info/RECORD
