Metadata-Version: 2.4
Name: update-notes-extractor
Version: 2025.12.21225744
Summary: update-notes-extractor is a package that extracts and structures release notes from software updates for easy, standardized, machine-readable summaries.
Author-email: update-notes-extractor <hi@eugene.plus>
License: MIT
Project-URL: Homepage, https://github.com/chigwell/update-notes-extractor
Requires-Python: >=3.9
Requires-Dist: langchain-llm7>=0.0.0
Requires-Dist: llmatch-messages>=0.0.0
Requires-Dist: langchain-core>=0.3.0
